smssia/DSA.py
smssia/OOP.py
smssia/OS.py
smssia/__init__.py
smssia-1.1.1.dist-info/METADATA
smssia-1.1.1.dist-info/WHEEL
smssia-1.1.1.dist-info/top_level.txt
smssia-1.1.1.dist-info/RECORD
