Metadata-Version: 2.1
Name: smssia
Version: 1.1.1
Requires-Dist: pyperclip
